README.md
setup.py
eve_cli/__init__.py
eve_cli/client.py
eve_cli/document.py
eve_cli/exceptions.py
eve_cli/resource.py
eve_cli.egg-info/PKG-INFO
eve_cli.egg-info/SOURCES.txt
eve_cli.egg-info/dependency_links.txt
eve_cli.egg-info/not-zip-safe
eve_cli.egg-info/top_level.txt