Metadata-Version: 1.0
Name: eve-cli
Version: 0.0.2
Summary: CLI utility to manage an EVE API
Home-page: http://github.com/SakiiR/eve-cli
Author: SakiiR
Author-email: sakiirlessons@gmail.com
License: MIT
Platform: UNKNOWN
